youtuber_ai_chatbot/__init__.py
youtuber_ai_chatbot/chatbot.py
youtuber_ai_chatbot/components/__init__.py
youtuber_ai_chatbot/components/faq.py
youtuber_ai_chatbot/components/sidebar.py
youtuber_ai_chatbot/components/youtube.py
youtuber_ai_chatbot/main.py
youtuber_ai_chatbot/prompts.py
youtuber_ai_chatbot-0.1.0.dist-info/LICENSE
youtuber_ai_chatbot-0.1.0.dist-info/METADATA
youtuber_ai_chatbot-0.1.0.dist-info/WHEEL
youtuber_ai_chatbot-0.1.0.dist-info/RECORD
