Metadata-Version: 2.1
Name: youtuber-ai-chatbot
Version: 0.1.0
Summary: Accurate answers for YouTube videos
License: MIT
Author: jorgik1
Requires-Python: >=3.10,<4.0
Classifier: License :: OSI Approved :: MIT License
Classifier: Programming Language :: Python :: 3
Classifier: Programming Language :: Python :: 3.10
Classifier: Programming Language :: Python :: 3.11
Requires-Dist: faiss-cpu (>=1.7.3,<2.0.0)
Requires-Dist: langchain (==0.0.79)
Requires-Dist: openai (>=0.26.2,<0.27.0)
Requires-Dist: streamlit (>=1.17.0,<2.0.0)
Requires-Dist: streamlit_elements (>=0.1,<0.2)
Requires-Dist: tiktoken (>=0.4.0,<0.5.0)
Requires-Dist: youtube-transcript-api (>=0.6.0,<0.7.0)
